num_theory/__init__.py
num_theory/arithmetic_progression.py
num_theory/get_primes.py
num_theory/is_prime.py
num_theory/prime_factorization.py
num_theory_euler_problems-0.2.7.dist-info/LICENSE
num_theory_euler_problems-0.2.7.dist-info/METADATA
num_theory_euler_problems-0.2.7.dist-info/WHEEL
num_theory_euler_problems-0.2.7.dist-info/RECORD
