Metadata-Version: 2.3
Name: num_theory_euler_problems
Version: 0.2.7
Summary: Implements different number theory functions
License: MIT
Author: Calista Chen, Dhruv Garg, Dominic Lam, Thamer Aldawood
Requires-Python: >=3.9
Classifier: License :: OSI Approved :: MIT License
Classifier: Programming Language :: Python :: 3
Classifier: Programming Language :: Python :: 3.9
Classifier: Programming Language :: Python :: 3.10
Classifier: Programming Language :: Python :: 3.11
Classifier: Programming Language :: Python :: 3.12
Classifier: Programming Language :: Python :: 3.13
